MANIFEST.in
README.rst
setup.py
SPHY/ET.py
SPHY/__init__.py
SPHY/advanced_routing.py
SPHY/dynamic_veg.py
SPHY/glac_table_with_iceDepths.csv
SPHY/glacier.py
SPHY/groundwater.py
SPHY/hargreaves.py
SPHY/lakes.py
SPHY/main.py
SPHY/reporting.py
SPHY/reservoirs.py
SPHY/rootzone.py
SPHY/routing.py
SPHY/snow.py
SPHY/sphy_config.cfg
SPHY/subzone.py
SPHY/timecalc.py
SPHY.egg-info/PKG-INFO
SPHY.egg-info/SOURCES.txt
SPHY.egg-info/dependency_links.txt
SPHY.egg-info/requires.txt
SPHY.egg-info/top_level.txt