Metadata-Version: 1.2
Name: SPHY
Version: 2.2.1
Summary: Spatial Processes in HYdrology (SPHY) model
Home-page: https://github.com/WilcoTerink/SPHY
Author: Wilco Terink
Author-email: terinkw@gmail.com
License: GPL-3.0
Keywords: Spatial Processes Hydrology Model Spatially-distributed pcraster
Platform: UNKNOWN
Classifier: Development Status :: 5 - Production/Stable
Classifier: Intended Audience :: Science/Research
Classifier: Intended Audience :: Developers
Classifier: Intended Audience :: End Users/Desktop
Classifier: Topic :: Scientific/Engineering
Classifier: Topic :: Scientific/Engineering :: GIS
Classifier: Topic :: Scientific/Engineering :: Mathematics
Classifier: Topic :: Scientific/Engineering :: Physics
Classifier: License :: OSI Approved :: GNU General Public License v3 (GPLv3)
Classifier: Programming Language :: Python :: 2.7
Requires-Python: ==2.7.*
